carbox/__init__.py
carbox/blocks.py
carbox/car.py
carbox/car_test.py
carbox/fixtures/donkeyballs.b64
carbox/jit.py
carbox/jit_test.py
carbox/message.py
carbox/varint.py
carbox/varint_test.py
carbox-0.3.dist-info/LICENSE
carbox-0.3.dist-info/METADATA
carbox-0.3.dist-info/WHEEL
carbox-0.3.dist-info/RECORD
