Metadata-Version: 2.1
Name: carbox
Version: 0.3
Summary: 
Home-page: https://github.com/jbn/carbox
License: MIT
Author: generativist
Author-email: jbn@abreka.com
Requires-Python: >=3.9,<4.0
Classifier: License :: OSI Approved :: MIT License
Classifier: Programming Language :: Python :: 3
Classifier: Programming Language :: Python :: 3.9
Classifier: Programming Language :: Python :: 3.10
Classifier: Programming Language :: Python :: 3.11
Classifier: Programming Language :: Python :: 3.12
Provides-Extra: optimized
Requires-Dist: cbor2 (>=5.4,<6.0)
Requires-Dist: dag-cbor (>=0.3,<0.4)
Requires-Dist: multiformats (>=0.3,<0.4)
Project-URL: Documentation, https://github.com/jbn/carbox
Project-URL: Repository, https://github.com/jbn/carbox
